quickrag/__init__.py
quickrag/quickrag.py
quickrag-0.2.1.dist-info/LICENSE
quickrag-0.2.1.dist-info/METADATA
quickrag-0.2.1.dist-info/WHEEL
quickrag-0.2.1.dist-info/top_level.txt
quickrag-0.2.1.dist-info/RECORD
