Metadata-Version: 2.1
Name: quickrag
Version: 0.2.1
Summary: A Quick Retrieval-Augmented Generation (RAG) system using transformers.
Home-page: https://github.com/VanshK7/quickrag
Author: Vansh Kharidia
Author-email: vanshkharidia7@gmail.com
Classifier: Programming Language :: Python :: 3
Classifier: License :: OSI Approved :: MIT License
Classifier: Operating System :: OS Independent
Requires-Python: >=3.6
License-File: LICENSE
Requires-Dist: torch (>=1.9.0)
Requires-Dist: numpy (>=1.19.2)
Requires-Dist: pandas (>=1.1.3)
Requires-Dist: tqdm (>=4.62.3)
Requires-Dist: sentence-transformers (>=2.1.0)
Requires-Dist: transformers (>=4.10.0)
Requires-Dist: PyMuPDF (>=1.19.0)
Requires-Dist: spacy (>=3.1.2)
Requires-Dist: textwrap3 (>=0.9.2)
Requires-Dist: bitsandbytes (>=0.27.2)
